{
  "products": [
    {
      "id": "1",
      "name": "Acoustic Plus",
      "image_url": "https://headphones.com/cdn/shop/products/72b00a38-3ee9-40db-9211-d4687f2866b2.png?v=1707787325&width=360",
      "description": "High-quality over-ear headphones with noise-cancellation.",
      "color_options": ["#000000", "#FFFFFF", "#FF5733"],
      "price": 299.99,
      "brand_name": "SoundMax",
      "ratings_stars": 4.5,
      "rating_counts": 150
    },
    {
      "id": "2",
      "name": "Bass Boost",
      "image_url": "https://headphones.com/cdn/shop/products/97acd4f3-656e-4d6e-b30c-98ced2b38696_d38e6d96-0ba6-45c6-9a55-fe8938c4c328.png?v=1707787388&width=360",
      "description": "Deep bass headphones with comfortable ear cushions.",
      "color_options": ["#0000FF", "#008000", "#FF0000"],
      "price": 199.99,
      "brand_name": "SoundMax",
      "ratings_stars": 4,
      "rating_counts": 200
    },
    {
      "id": "3",
      "name": "Crystal Clear",
      "image_url": "https://headphones.com/cdn/shop/products/BATHYS_34_02.jpg?v=1707786814&width=360",
      "description": "In-ear headphones with crystal clear sound and ergonomic design.",
      "color_options": ["#FFD700", "#C0C0C0", "#000000"],
      "price": 99.99,
      "brand_name": "AudioTech",
      "ratings_stars": 4.7,
      "rating_counts": 320
    },
    {
      "id": "4",
      "name": "Dynamic Sound",
      "image_url": "https://headphones.com/cdn/shop/products/Celestee11024x1024.jpg?v=1707787769&width=360",
      "description": "Wireless headphones with dynamic sound and long battery life.",
      "color_options": ["#800080", "#FF69B4", "#4B0082"],
      "price": 249.99,
      "brand_name": "WirelessPro",
      "ratings_stars": 4.3,
      "rating_counts": 175
    },
    {
      "id": "5",
      "name": "Elite Noise-Canceling",
      "image_url": "https://headphones.com/cdn/shop/products/5bcd13c5-0301-4520-9fa4-22a7e2f10ee2_c6082a11-05b9-45a8-86ec-844fa1953cfc.png?v=1707787308&width=360",
      "description": "Premium noise-canceling headphones with superior comfort.",
      "color_options": ["#00CED1", "#2E8B57", "#8B0000"],
      "price": 349.99,
      "brand_name": "QuietComfort",
      "ratings_stars": 4.8,
      "rating_counts": 250
    },
    {
      "id": "6",
      "name": "Fitness Buds",
      "image_url": "https://headphones.com/cdn/shop/products/ThieaudioMonarchMKII1024x1024.jpg?v=1707787750&width=360",
      "description": "Sweat-proof in-ear headphones designed for workouts.",
      "color_options": ["#FF4500", "#7FFF00", "#1E90FF"],
      "price": 79.99,
      "brand_name": "SportSound",
      "ratings_stars": 4.1,
      "rating_counts": 180
    },
    {
      "id": "7",
      "name": "Gaming Pro",
      "image_url": "https://headphones.com/cdn/shop/products/AudezeLCD-XSuspensionHB1024x1024.jpg?v=1707787306&width=360",
      "description": "High-fidelity gaming headphones with a built-in microphone.",
      "color_options": ["#FF1493", "#FFD700", "#00BFFF"],
      "price": 129.99,
      "brand_name": "GameAudio",
      "ratings_stars": 4.6,
      "rating_counts": 220
    },
    {
      "id": "8",
      "name": "Harmony",
      "image_url": "https://headphones.com/cdn/shop/products/Arya_1._1024x1024_daa11a22-0827-4f77-9823-3a048b84d599.jpg?v=1707787535&width=360",
      "description": "Over-ear headphones with balanced sound and comfortable fit.",
      "color_options": ["#ADFF2F", "#FF6347", "#8A2BE2"],
      "price": 179.99,
      "brand_name": "AudioTech",
      "ratings_stars": 4.2,
      "rating_counts": 140
    },
    {
      "id": "9",
      "name": "Immersive Experience",
      "image_url": "https://headphones.com/cdn/shop/products/FocalRadiance61024x1024color.jpg?v=1707787660&width=360",
      "description": "Headphones with immersive sound and active noise-canceling.",
      "color_options": ["#A52A2A", "#DEB887", "#5F9EA0"],
      "price": 289.99,
      "brand_name": "SoundMax",
      "ratings_stars": 4.7,
      "rating_counts": 190
    },
    {
      "id": "10",
      "name": "Jet Black",
      "image_url": "https://headphones.com/cdn/shop/products/FocalClearMg11024x1024.jpg?v=1707787788&width=360",
      "description": "Sleek and stylish black headphones with rich sound.",
      "color_options": ["#000000"],
      "price": 159.99,
      "brand_name": "GameAudio",
      "ratings_stars": 4.3,
      "rating_counts": 210
    },
    {
      "id": "11",
      "name": "Kids Safe Sound",
      "image_url": "https://headphones.com/cdn/shop/products/722e5a50-e5e6-4cae-a2ab-4d6617f2345f_008b0912-c796-4d8b-a4ca-3b69f6547cb6.png?v=1707787660&width=360",
      "description": "Volume-limited headphones designed for kids' safety.",
      "color_options": ["#FF69B4", "#8A2BE2", "#FFD700"],
      "price": 39.99,
      "brand_name": "SafeKids",
      "ratings_stars": 4.5,
      "rating_counts": 90
    },
    {
      "id": "12",
      "name": "Luxury Leather",
      "image_url": "https://headphones.com/cdn/shop/products/Ananda_1024x1024.jpg?v=1707787388&width=360",
      "description": "Luxury headphones with leather ear pads and high-definition sound.",
      "color_options": ["#8B4513", "#D2691E", "#A0522D"],
      "price": 399.99,
      "brand_name": "EliteSound",
      "ratings_stars": 4.9,
      "rating_counts": 160
    },
    {
      "id": "13",
      "name": "Modern Minimal",
      "image_url": "https://headphones.com/cdn/shop/products/011fc321-c98a-4ffc-8074-a7997ac8974d_691ce7a0-10ce-4453-ab7d-8352c50c1859.png?v=1707787370&width=360",
      "description": "Minimalist design headphones with clear sound.",
      "color_options": ["#808080", "#FFFFFF", "#000000"],
      "price": 149.99,
      "brand_name": "GameAudio",
      "ratings_stars": 4,
      "rating_counts": 130
    },
    {
      "id": "14",
      "name": "NoiseBlocker",
      "image_url": "https://headphones.com/cdn/shop/products/Stellia_1_1024x1024_d1a97a22-004b-4139-8b7f-b2f6a92c14c5.jpg?v=1707787412&width=360",
      "description": "Effective noise-canceling headphones for a distraction-free experience.",
      "color_options": ["#696969", "#A9A9A9", "#000000"],
      "price": 259.99,
      "brand_name": "QuietTunes",
      "ratings_stars": 4.6,
      "rating_counts": 180
    },
    {
      "id": "15",
      "name": "Outdoor Adventure",
      "image_url": "https://headphones.com/cdn/shop/products/HifimanHE400se11024x1024.jpg?v=1707787933&width=360",
      "description": "Rugged and durable headphones for outdoor use.",
      "color_options": ["#228B22", "#556B2F", "#8FBC8F"],
      "price": 139.99,
      "brand_name": "QuietTunes",
      "ratings_stars": 4.3,
      "rating_counts": 110
    },
    {
      "id": "16",
      "name": "Premium Performance",
      "image_url": "https://headphones.com/cdn/shop/products/AudezeLCD-XCCarbon1024x1024.jpg?v=1707787632&width=360",
      "description": "High-performance headphones with exceptional sound quality.",
      "color_options": ["#FF0000", "#000000", "#FFFFFF"],
      "price": 299.99,
      "brand_name": "ProSound",
      "ratings_stars": 4.7,
      "rating_counts": 200
    },
    {
      "id": "17",
      "name": "Quiet Comfort",
      "image_url": "https://headphones.com/cdn/shop/products/0fc678b9-bc83-4f8a-9799-ee5b9f3c680b.png?v=1707787684&width=360",
      "description": "Comfortable and quiet headphones for long listening sessions.",
      "color_options": ["#2F4F4F", "#696969", "#808080"],
      "price": 219.99,
      "brand_name": "QuietComfort",
      "ratings_stars": 4.4,
      "rating_counts": 150
    },
    {
      "id": "18",
      "name": "Studio Master",
      "image_url": "https://headphones.com/cdn/shop/products/AudezeMM-5001024x1024.jpg?v=1707788537&width=360",
      "description": "Professional studio headphones with accurate sound reproduction.",
      "color_options": ["#000000", "#C0C0C0", "#FFD700"],
      "price": 349.99,
      "brand_name": "QuietTunes",
      "ratings_stars": 4.8,
      "rating_counts": 210
    },
    {
      "id": "19",
      "name": "Travel Light",
      "image_url": "https://headphones.com/cdn/shop/products/SennheiserIE9001024x1024.jpg?v=1707787933&width=360",
      "description": "Lightweight and portable headphones perfect for travel.",
      "color_options": ["#B0E0E6", "#4682B4", "#5F9EA0"],
      "price": 129.99,
      "brand_name": "ProSound",
      "ratings_stars": 4.2,
      "rating_counts": 170
    },
    {
      "id": "20",
      "name": "Urban Beats",
      "image_url": "https://headphones.com/cdn/shop/products/MarkLevinson5909Black51024x1024.jpg?v=1707788457&width=360",
      "description": "Stylish headphones with powerful sound for urban lifestyle.",
      "color_options": ["#DC143C", "#000000", "#FFFFFF"],
      "price": 159.99,
      "brand_name": "CityAudio",
      "ratings_stars": 4.3,
      "rating_counts": 190
    }
  ],
  "colors": [
    "#FFD700",
    "#C0C0C0",
    "#000000",
    "#800080",
    "#FF69B4",
    "#4B0082",
    "#00CED1",
    "#2E8B57",
    "#8B0000",
    "#FF4500",
    "#7FFF00",
    "#1E90FF",
    "#FF1493",
    "#00BFFF",
    "#ADFF2F",
    "#FF6347",
    "#8A2BE2",
    "#A52A2A",
    "#DEB887",
    "#5F9EA0",
    "#8B4513",
    "#D2691E",
    "#A0522D",
    "#808080",
    "#FFFFFF",
    "#696969",
    "#A9A9A9",
    "#228B22",
    "#556B2F",
    "#8FBC8F",
    "#FF0000",
    "#2F4F4F",
    "#B0E0E6",
    "#4682B4"
  ],
  "brands": [
    "SoundMax",
    "AudioTech",
    "WirelessPro",
    "QuietComfort",
    "SportSound",
    "GameAudio",
    "QuietTunes",
    "EliteSound",
    "ProSound",
    "CityAudio"
  ]
}


